shopify_app/__init__.py
shopify_app/_version.py
shopify_app/py.typed
shopify_app/types.py
shopify_app/exchange/__init__.py
shopify_app/exchange/_response_builders.py
shopify_app/exchange/_validation.py
shopify_app/exchange/client_credentials.py
shopify_app/exchange/refresh_token.py
shopify_app/exchange/token_exchange.py
shopify_app/graphql/__init__.py
shopify_app/graphql/admin_graphql.py
shopify_app/helpers/__init__.py
shopify_app/helpers/app_home_parent_redirect.py
shopify_app/helpers/app_home_patch_id_token.py
shopify_app/helpers/app_home_redirect.py
shopify_app/utils/__init__.py
shopify_app/utils/headers.py
shopify_app/utils/http_client.py
shopify_app/utils/input_converters.py
shopify_app/utils/user_agent.py
shopify_app/verify/__init__.py
shopify_app/verify/_body_hmac_in_header.py
shopify_app/verify/_non_exchangeable_id_token.py
shopify_app/verify/admin_ui_ext.py
shopify_app/verify/app_home_req.py
shopify_app/verify/app_proxy.py
shopify_app/verify/checkout_ui_ext.py
shopify_app/verify/customer_account_ui_ext.py
shopify_app/verify/flow_action.py
shopify_app/verify/pos_ui_ext.py
shopify_app/verify/webhook.py
shopifyapp-0.1.0.dist-info/METADATA
shopifyapp-0.1.0.dist-info/WHEEL
shopifyapp-0.1.0.dist-info/licenses/LICENSE
shopifyapp-0.1.0.dist-info/RECORD
