Metadata-Version: 2.4
Name: shopifyapp
Version: 0.1.0
Summary: Package for building Shopify applications. Authored and maintained by Shopify.
Project-URL: homepage, https://github.com/Shopify/shopify-app-python/
Project-URL: issues, https://community.shopify.dev/c/shopify-cli-libraries/14
Project-URL: changelog, https://github.com/Shopify/shopify-app-python/blob/main/CHANGELOG.md
Author: Shopify
License: Copyright (c) 2025 Shopify Inc.
License-File: LICENSE
Keywords: admin-graphql,app-proxy,client-credentials,flow-action,shopify,token-exchange,webhooks
Classifier: Development Status :: 4 - Beta
Classifier: Intended Audience :: Developers
Classifier: License :: OSI Approved :: MIT License
Classifier: Programming Language :: Python :: 3
Classifier: Programming Language :: Python :: 3.8
Classifier: Programming Language :: Python :: 3.9
Classifier: Programming Language :: Python :: 3.10
Classifier: Programming Language :: Python :: 3.11
Classifier: Programming Language :: Python :: 3.12
Classifier: Programming Language :: Python :: 3.13
Classifier: Topic :: Software Development :: Libraries :: Python Modules
Requires-Python: >=3.8
Requires-Dist: httpx>=0.24.0
Requires-Dist: pyjwt>=2.8.0
